LICENSE
MANIFEST.in
README.rst
setup.py
sphinx_naps_theme/__init__.py
sphinx_naps_theme.egg-info/PKG-INFO
sphinx_naps_theme.egg-info/SOURCES.txt
sphinx_naps_theme.egg-info/dependency_links.txt
sphinx_naps_theme.egg-info/top_level.txt
sphinx_naps_theme/ext/__init__.py
sphinx_naps_theme/ext/flask_theme_support.py
sphinx_naps_theme/themes/naps/.relations.html.swp
sphinx_naps_theme/themes/naps/layout.html
sphinx_naps_theme/themes/naps/relations.html
sphinx_naps_theme/themes/naps/theme.conf
sphinx_naps_theme/themes/naps/static/.flasky.css_t.swp
sphinx_naps_theme/themes/naps/static/GenBkBasR.ttf
sphinx_naps_theme/themes/naps/static/flasky.css_t
sphinx_naps_theme/themes/naps/static/small_flask.css