Metadata-Version: 1.0
Name: sphinx-naps-theme
Version: 1
Summary: Sphinx theme used by Antoine Millet for its projects
Home-page: UNKNOWN
Author: Antoine Millet
Author-email: antoine@inaps.org
License: UNKNOWN
Platform: UNKNOWN
